s3tk/__init__.py
s3tk/checks.py
s3tk-0.5.0.dist-info/licenses/LICENSE.txt
s3tk-0.5.0.dist-info/METADATA
s3tk-0.5.0.dist-info/WHEEL
s3tk-0.5.0.dist-info/entry_points.txt
s3tk-0.5.0.dist-info/top_level.txt
s3tk-0.5.0.dist-info/RECORD
