Metadata-Version: 2.4
Name: s3tk
Version: 0.5.0
Summary: A security toolkit for Amazon S3
Author-email: Andrew Kane <andrew@ankane.org>
License-Expression: BSD-3-Clause
Project-URL: Homepage, https://github.com/ankane/s3tk
Requires-Python: >=3.10
License-File: LICENSE.txt
Requires-Dist: boto3>=1.9.46
Requires-Dist: botocore>=1.12.46
Requires-Dist: clint
Requires-Dist: click
Requires-Dist: joblib
Dynamic: license-file
